molecule_info/__init__.py
molecule_info/molecule_info.py
molecule_info/utils.py
molecule_info-1.0.1.dist-info/METADATA
molecule_info-1.0.1.dist-info/WHEEL
molecule_info-1.0.1.dist-info/licenses/LICENSE
molecule_info-1.0.1.dist-info/RECORD
