Metadata-Version: 2.4
Name: molecule-info
Version: 1.0.1
Summary: 
License-File: LICENSE
Author: tobiaspk
Author-email: tobiaspk1@gmail.com
Requires-Python: >=3.8,<4.0
Classifier: Programming Language :: Python :: 3
Classifier: Programming Language :: Python :: 3.8
Classifier: Programming Language :: Python :: 3.9
Classifier: Programming Language :: Python :: 3.10
Classifier: Programming Language :: Python :: 3.11
Classifier: Programming Language :: Python :: 3.12
Classifier: Programming Language :: Python :: 3.13
Classifier: Programming Language :: Python :: 3.14
Requires-Dist: anndata (>=0.8.0,<0.9.0)
Requires-Dist: h5py (>=3.0.0,<4.0.0)
Requires-Dist: pandas (>=2.0.0,<3.0.0)
Requires-Dist: scikit-learn (>=1.3.2,<2.0.0)
